wildbits/__init__.py
wildbits/__main__.py
wildbits/__version__.py
wildbits/_rstb.py
wildbits/_sarc.py
wildbits/_yaml.py
wildbits/util.py
wildbits/assets/index.html
wildbits/assets/scripts/bundle.js
wildbits-1.1.2.dist-info/METADATA
wildbits-1.1.2.dist-info/WHEEL
wildbits-1.1.2.dist-info/entry_points.txt
wildbits-1.1.2.dist-info/top_level.txt
wildbits-1.1.2.dist-info/RECORD
