Metadata-Version: 2.1
Name: wildbits
Version: 1.1.2
Summary: Simple GUI editor for BOTW file formats
Home-page: https://github.com/NiceneNerd/Wild-Bits/
Author: NiceneNerd
Author-email: macadamiadaze@gmail.com
License: GPLv3
Platform: UNKNOWN
Classifier: Development Status :: 5 - Production/Stable
Classifier: License :: OSI Approved :: GNU General Public License v3 or later (GPLv3+)
Classifier: Programming Language :: Python :: 3.7
Requires-Python: >=3.7
Requires-Dist: botw-utils (>=0.2.2)
Requires-Dist: oead (>=1.1.1)
Requires-Dist: rstb (>=1.2.0)
Requires-Dist: pymsyt (~=0.3.2)
Requires-Dist: xxhash
Requires-Dist: pywebview (<4.0,>=3.2)
Requires-Dist: cefpython3 (~=66.0) ; platform_system == "Windows"
